src/__init__.py
src/cryoemDataset.py
src/dataset_resample.py
src/evaluator.py
src/utils.py
src/cs_star_translate/__init__.py
src/cs_star_translate/cs2star.py
src/cs_star_translate/generate_cs_file.py
src/cs_star_translate/utils.py
src/cs_star_translate/pyem/__init__.py
src/cs_star_translate/pyem/ctf.py
src/cs_star_translate/pyem/mrc.py
src/cs_star_translate/pyem/plot.py
src/cs_star_translate/pyem/star.py
src/cs_star_translate/pyem/algo/__init__.py
src/cs_star_translate/pyem/algo/algo.py
src/cs_star_translate/pyem/algo/algo_numba.py
src/cs_star_translate/pyem/geom/__init__.py
src/cs_star_translate/pyem/geom/convert.py
src/cs_star_translate/pyem/geom/convert_numba.py
src/cs_star_translate/pyem/geom/geom.py
src/cs_star_translate/pyem/geom/geom_numba.py
src/cs_star_translate/pyem/geom/quat.py
src/cs_star_translate/pyem/geom/quat_numba.py
src/cs_star_translate/pyem/metadata/__init__.py
src/cs_star_translate/pyem/metadata/cistem.py
src/cs_star_translate/pyem/metadata/cryosparc0.py
src/cs_star_translate/pyem/metadata/cryosparc2.py
src/cs_star_translate/pyem/util/__init__.py
src/cs_star_translate/pyem/util/util.py
src/cs_star_translate/pyem/vop/__init__.py
src/cs_star_translate/pyem/vop/binary.py
src/cs_star_translate/pyem/vop/vop.py
src/cs_star_translate/pyem/vop/vop_numba.py
src/data_preprocess/__init__.py
src/data_preprocess/fft.py
src/data_preprocess/lmdb_preprocess.py
src/data_preprocess/mrc.py
src/data_preprocess/mrc_preprocess.py
cryoief_data-0.1.0.dist-info/METADATA
cryoief_data-0.1.0.dist-info/WHEEL
cryoief_data-0.1.0.dist-info/top_level.txt
cryoief_data-0.1.0.dist-info/RECORD
